{
    "chapterId": "what-is-it",
    "title": "What is it?",
    "pages": [
        {
            "pageId": 3,
            "transition": "push",
            "layout": "two-column",
            "media": {
                "mediaId": "mitosis-colony",
                "marker": "end",
                "loop": true
            },
            "body": {
                "transition": "",
                "content": [
                    {
                        "text": "Mitosis is one of the most visually striking and most studied cell behaviors. \nDuring this stepwise process, cells segregate their replicated DNA and other contents, then divide into two.",
                        "element": "p",
                        "type": "text"
                    }
                ]
            }
        }
    ]
}